tek_secrets/__init__.py
tek_secrets/core/auth.py
tek_secrets/core/clean.py
tek_secrets/core/config.py
tek_secrets/core/utils.py
tek_secrets/environment.py
tek_secrets/main.py
tek_secrets/projects.py
tek_secrets-0.1.8.dist-info/METADATA
tek_secrets-0.1.8.dist-info/WHEEL
tek_secrets-0.1.8.dist-info/entry_points.txt
tek_secrets-0.1.8.dist-info/RECORD
