Metadata-Version: 2.3
Name: tek-secrets
Version: 0.1.8
Summary: Tek Secrets CLI
License: MIT
Author: Luis
Author-email: lespinerua@gmail.com
Requires-Python: >=3.9,<4.0
Classifier: License :: OSI Approved :: MIT License
Classifier: Programming Language :: Python :: 3
Classifier: Programming Language :: Python :: 3.9
Classifier: Programming Language :: Python :: 3.10
Classifier: Programming Language :: Python :: 3.11
Classifier: Programming Language :: Python :: 3.12
Classifier: Programming Language :: Python :: 3.13
Requires-Dist: cli-oauth2 (>=0.3.1,<0.4.0)
Requires-Dist: dotenv (>=0.9.9,<0.10.0)
Requires-Dist: inquirer (>=3.4.0,<4.0.0)
Requires-Dist: keyring (>=25.6.0,<26.0.0)
Requires-Dist: oauth2-cli-auth (>=1.6.1,<2.0.0)
Requires-Dist: pygithub (==2.5.0)
Requires-Dist: python-dotenv (>=1.1.0,<2.0.0)
Requires-Dist: requests (==2.32.3)
Requires-Dist: starlette (>=0.46.1,<0.47.0)
Requires-Dist: typer (>=0.15.2,<0.16.0)
